{"pubtype":"InProceedings","citekey":"ahmad-kondrak:2005:HLTEMNLP","author":"Ahmad, Farooq and Kondrak, Grzegorz","title":"Learning a Spelling Error Model from Search Query Logs","booktitle":"Proceedings of Human Language Technology Conference and Conference on Empirical Methods in Natural Language Processing","month":"October","year":"2005","address":"Vancouver, British Columbia, Canada","publisher":"Association for Computational Linguistics","pages":"955--962","url":"http://www.aclweb.org/anthology/H/H05/H05-1120"}
