{"pubtype":"InProceedings","citekey":"azzam-humphreys-gaizauskas:1998:ACLCOLING","author":"Saliha Azzam and Kevin Humphreys and Robert Gaizauskas","title":"Evaluating a Focus-Based Approach to Anaphora Resolution","booktitle":"Proceedings of the 36th Annual Meeting of the Association for Computational Linguistics and 17th International Conference on Computational Linguistics, Volume 1","month":"August","year":"1998","address":"Montreal, Quebec, Canada","publisher":"Association for Computational Linguistics","pages":"74--78","url":"http://www.aclweb.org/anthology/P98-1011","doi":"10.3115/980845.980858"}
