{"pubtype":"InProceedings","citekey":"kumar-padro-oliver:2015:RANLP2015","author":"Kumar, Arun and Padró, Lluís and Oliver, Antoni","title":"Learning Agglutinative Morphology of Indian Languages with Linguistically Motivated Adaptor Grammars","booktitle":"Proceedings of the International Conference Recent Advances in Natural Language Processing","month":"September","year":"2015","address":"Hissar, Bulgaria","publisher":"INCOMA Ltd. Shoumen, BULGARIA","pages":"307--312","url":"http://www.aclweb.org/anthology/R15-1041"}
