{"pubtype":"inproceedings","citekey":"TAHON12.853.L12-1508","author":"Marie Tahon and Agnes Delaborde and Laurence Devillers","url":"http://www.lrec-conf.org/proceedings/lrec2012/pdf/853_Paper.pdf","note":"ACL Anthology Identifier: L12-1508","title":"Corpus of Children Voices for Mid-level Markers and Affect Bursts Analysis","booktitle":"Proceedings of the Eighth International Conference on Language Resources and Evaluation (LREC-2012)","year":"2012","month":"May","address":"Istanbul, Turkey","editor":"Nicoletta Calzolari and Khalid Choukri and Thierry Declerck and Mehmet Uğur Doğan and Bente Maegaard and Joseph Mariani and Jan Odijk and Stelios Piperidis","publisher":"European Language Resources Association (ELRA)","isbn":"978-2-9517408-7-7","language":"English","pages":"2366--2369"}
