{"pubtype":"InProceedings","citekey":"bollegala-matsuo-ishizuka:2006:CLIIR","author":"Bollegala, Danushka and Matsuo, Yutaka and Ishizuka, Mitsuru","title":"Extracting Key Phrases to Disambiguate Personal Name Queries in Web Search","booktitle":"Proceedings of the Workshop on How Can Computational Linguistics Improve Information Retrieval?","month":"July","year":"2006","address":"Sydney, Australia","publisher":"Association for Computational Linguistics","pages":"17--24","url":"http://www.aclweb.org/anthology/W/W06/W06-0803"}
