{"pubtype":"InProceedings","citekey":"kochmar-briscoe:2013:RANLP-2013","author":"Kochmar, Ekaterina and Briscoe, Ted","title":"Capturing Anomalies in the Choice of Content Words in Compositional Distributional Semantic Space","booktitle":"Proceedings of the International Conference Recent Advances in Natural Language Processing RANLP 2013","month":"September","year":"2013","address":"Hissar, Bulgaria","publisher":"INCOMA Ltd. Shoumen, BULGARIA","pages":"365--372","url":"http://www.aclweb.org/anthology/R13-1047"}
