{"pubtype":"InProceedings","citekey":"garrette-EtAl:2015:NAACL-HLT","author":"Garrette, Dan and Alpert-Abrams, Hannah and Berg-Kirkpatrick, Taylor and Klein, Dan","title":"Unsupervised Code-Switching for Multilingual Historical Document Transcription","booktitle":"Proceedings of the 2015 Conference of the North American Chapter of the Association for Computational Linguistics: Human Language Technologies","month":"May--June","year":"2015","address":"Denver, Colorado","publisher":"Association for Computational Linguistics","pages":"1036--1041","url":"http://www.aclweb.org/anthology/N15-1109"}
