{"pubtype":"InProceedings","citekey":"ludusan-synnaeve-dupoux:2015:NAACL-HLT","author":"Ludusan, Bogdan and Synnaeve, Gabriel and Dupoux, Emmanuel","title":"Prosodic boundary information helps unsupervised word segmentation","booktitle":"Proceedings of the 2015 Conference of the North American Chapter of the Association for Computational Linguistics: Human Language Technologies","month":"May--June","year":"2015","address":"Denver, Colorado","publisher":"Association for Computational Linguistics","pages":"953--963","url":"http://www.aclweb.org/anthology/N15-1096"}
