{"sections":[{"title":"!\"##$%&#'()*)+,-&#(&.(#&/#0-&*.&#(+&(.&1.&( 2,*)/-&(304&+\"//&5&*.( 6).#$78(20%90+)(&.(3\"5$*$:9&(;)9#&*.(","paragraphs":["2,*)/-&(304&+\"//&5&*.'(<<(#9&(=),*)#>'(<?@@@(A\"9+\"9-&( !\"#$%&'()*+,*-\".)/0\"!)*12(&3456-\",$*0#.)/0\"!)*12$(&345 BC2D=C((EEEEEEEEEEEEEEEEEEEEEEEEEEEEEEEEEEEEEEEEEEEEEEEEEEEEEEEEEEEEEEEEEEEEEEEEEEEEEEEEEEEEEEEEEEEEEE(( 2,*)/-&( 304&+\"//&5&*.( -\"9F)$.&( 07F)*%&#( )4&7( +&-( 7\"*G0#&*7$&#-( )9.\"9#( >&-( .&7F*\"+\"%$&-( :9H&++&(7\"55&#7$)+$-&(I(7\"##&7.$\"*(>&(.&1.&-(&.()*)+,-&(-05)*.$:9&J( 6+9-$&9#-( /#\">9$.-( &.( >05\"*-.#).&9#-( -&#\"*.( /#0-&*.0-'( *\".#&( K9.( 0.)*.( >H$*-.)9#&#( 9*( >$)+\"%9&( &.( >&( 7\"*G#\"*.&#( *\".#&( )//#\"7F&( >9( AL;'( M( K)-&( >&( 50.F\">&-( -,5K\"+$:9&-( &.( -.).$-.$:9&-( $*G+9&*70&-( /)#( >&-( 7\"*.#)$*.&-( >&( /#\">97.$\"*'( &.( 7&++&-( 9.$+$-0&-( /)#( +&-( 7F&#7F&9#-'($*>9-.#$&+-(\"9(/)--$\"**0-(:9$(4$&*>#\"*.(M(*\".#&(#&*7\"*.#&J( LN2ABL!A(EEEEEEEEEEEEEEEEEEEEEEEEEEEEEEEEEEEEEEEEEEEEEEEEEEEEEEEEEEEEEEEEEEEEEEEEEEEEEEEEEEEEEEEEEEEEE(( !F&78$*%'()*)+,-$*%()*>(#&/#&-&*.$*%(.&1.-( 2,*)/-&( 304&+\"//&5&*.( O\"9+>( +$8&( .\"( >&5\"*-.#).&( $.-( %#)55)#( 7F&78&#( )*>( -&5)*.$7( )*)+,-$-(.&7F*\"+\"%$&-(.\"(\"/&*(&17$.$*%(>$-79--$\"*-(O$.F(*).9#)+(+)*%9)%&(-/&7$)+$-.-J(P&()#&( /)#.$79+)#+,($*.&#&-.&>($*(>$-79--$*%(.F&(-7$&*.$G$7($--9&-(O&(F)4&(.\"(G)7&()*>(-\"+4&()77\"#>$*%( .\"(\"9#($*>9-.#$)+(*&&>-J( =QA2R!;C2(I"]},{"title":"(","paragraphs":["!\"##&7.$\"*( %#)55).$7)+&'( )*)+,-&( -,*.)1$:9&'( )*)+,-&( -05)*.$:9&'( )*)+,-&( >H\"/$*$\"*-J(( STUPQB32(I(V#)55)#(7F&78&#'(6Q2(.)%%$*%'(-&5)*.$7()*)+,-$-'(\"/$*$\"*(5$*$*%J("]},{"title":"? !\"##&7.$\"*(>&(.&1.&(","paragraphs":["D*&(/#&5$W#&(>05\"*-.#).$\"*(/\"#.&#)(-9#(+&(5\".&9#(>&(7\"##&7.$\"*(%#)55).$7)+&(>9(G#)*X)$-J( ;&(G\"*7.$\"**&5&*.(>&(7&(>&#*$&#()(>0YM(0.0(/#0-&*.0()91(7\"*G0#&*7&-(AL;Z([@@\\(];)9#&*.(&.( )+'([@@\\Ĵ(( ;&( 5\".&9#( _<( @@@( #W%+&-( >&( %#)55)$#&( K)-0&-( -9#( ?( à@( @@@( $*G\"#5).$\"*-( %#)55).$7)+&-(&.(-05)*.$:9&-J(L9R>&+M(>&(+H)-/&7.(G\"*7.$\"**&+'(4$-$K+&(-9#(+&(/#\">9$.(!\"#>$)+'( *\"9-( 5\"*.#&#\"*-( 7\"55&*.( -\"*.( 7\"*-.#9$.&-( 7&-( #W%+&-( &.( +&-( \"9.$+-( :9&( *\"9-( 5&..\"*-( &*( /+)7&(/\"9#(.\"9Y\"9#-(+&-(G)$#&(04\"+9&#(&*(G\"*7.$\"*(>&-(\"//\"#.9*$.0-(.&7F*\"+\"%$:9&-(*\"94&++&-( ]#0-&)91(-\"7$)91'(-$.&-(/)#.$7$/).$G-()4&7(505\"$#&(>H0>$.$\"*'(&.7J(̂];)9#&*.'([@?['̂(]N&)9G\"#.( &.()+'([@?@'̂(]P$-*$&O-8$(&.()+'([@?@Ĵ( 3H9*( /\"$*.( >&( 49&( /+9-( .&7F*$:9&'( *\"9-( /#0-&*.&#\"*-( 7\"55&*.( *\"9-( )##$4\"*-( M( 5)$*.&*$#( 9*&(4$.&--&(>&(.#)$.&5&*.(-9/0#$&9#&(M(?@(@@@(5\".-b-&7\"*>&(-9#(9*&(5)7F$*&(>9(7\"55&#7&( &*(9.$+$-)*.(.\"9Y\"9#-(/+9-(>&(#&--\"9#7&-(+$*%9$-.$:9&-(>)*-(*\".#&(5\".&9#J("]},{"title":"[ L*)+,-&(>&(.&1.&(","paragraphs":["2,*)/-&( 304&+\"//&5&*.( )*)+,-&( +&-( .&1.&-( 07#$.-'( *\"*( -.#97.9#0-( &.( +&-( #&/#0-&*.&( -\"9-( G\"#5&( >H\"KY&.-J( !&-( \"KY&.-( -\"*.( &*-9$.&( \"#%)*$-0-( /\"9#( /#\"/\"-&#( >&-( )//+$7).$\"*-( M( F)9.&( TALN-RÉCITAL 2013, 17-21 Juin, Les Sables d’Olonne 795 c⃝ ATALA !\"#$%&' \"()%*+$,' -./0+$' 0$' 1$**$' 2$1)30$' 0+4)32*&\"*/)3' $2*' 0$' 5&+2$3*$&' 5#%2/$%&2' \"55#/1\"*/)32'\"%*)%&'0$'*$163)#)7/$2'0.\"3\"#82$'0$'*$9*$'$*'0.+16\"37$&'2%&'#\"'*$163)#)7/$'$##$: 4;4$'\"/32/'<%$'2%&'#$2'0/==+&$3*$2'!/2%\"#/2\"*/)32'0$2'&+2%#*\"*2'/22%2'0$'1$2'*$163)#)7/$2,'>$2' 0+4)32*&\"*/)32'2)3*'0/25)3/?#$2'2%&'#$'@#\"?@'0$'A83\"52$,' -$2' *$163)#)7/$2' 5&+2$3*+$2' 2$&)3*' #.+*/<%$*\"7$' 4)&56):283*\"9/<%$' B-\"%&$3*' $*' \"#C' DEEFGC' #.\"3\"#82$' 1)31$5*%$##$C' #.H9*&\"1*/)3' 0.$3*/*+2' 3)44+$2' $*' #.\"3\"#82$' 0.)5/3/)3' B>6\"&0)3C' DEIJG,' -$2'\"55#/1\"*/)32'2$&)3*'#$2'2%/!\"3*$2'K'' I,'L3)384/2\"*/)3'0$'*$9*$2' D,' >&+\"*/)3' \"%*)4\"*/<%$' 0$' 4+*\"0)33+$2' 5)%&' #./30$9\"*/)3C' #\"' &$16$&16$' $*' #\"' 4/2$' $3' &$#\"*/)3'0$'1)3*$3%2'5&)16$2' J,' M' 5\"&*/&' 0$' 1)44$3*\"/&$2' 0$' &$2*\"%&\"3*2' K' &$1)33\"/22\"31$' 0$2' 5#\"*2' 2$&!/2C' 5&+=+&+2' $*' 0+1)32$/##+2' 5)%&' %3' +*\"?#/22$4$3*,' N!\"#%\"*/)3' \"%*)4\"*/<%$' 0$2' &$2*\"%&\"3*2' 2%&' 5#%2/$%&2' 1&/*O&$2'&$1)33%2'\"%*)4\"*/<%$4$3*'K'1%/2/3$C'\"4?/\"31$C'2$&!/1$C'$*1,' P,'L3\"#82$'0$'#\"'*)3\"#/*+'0$'1)44$3*\"/&$2'2%&'%3$'4\"&<%$'Q'5\"&*/&'0$2'&+2$\"%9'2)1/\"%9'$*'=#%9' RAA,' S,' >&+\"*/)3' 0$' 5\"&1)%&2' 0$' #$1*%&$' 0$' *$9*$2' /22%2' 1)44$3*\"/&$2' K' )&/$3*\"*/)3' B5)2/*/!$T3+7\"*/!$GC'/3*$32/*+C'3\"*%&$'B1)32$/#C'(%7$4$3*C'2$3*/4$3*G,'"]},{"title":"––'","paragraphs":["UHLVWXRY' R,' RXHZ[LVY' A,' >XV\\]X]' -,' $*' WLR̂X]' >,' BDEIEG,' V3$' \"55&)16$' 68?&/0$' *&\"0%1*/)3T1)&&$1*/)3' 5)%&' #\"' 3)&4\"#/2\"*/)3' 0$2' A_A,' L1*$2' 0$' YL-]' DEIE' BY&\"/*$4$3*' \"%*)4\"*/<%$'0$2'#\"37%$2'3\"*%&$##$2GC'_)3*&+\"#,'LYL-L,' >[LRX̀]' U,' UH]L_LRL'W,' aXaHA>V'b' _LY[ĤV' c,' $*' L26$&' ],' BDEIJG,' _$\"2%&/37' *6$' H==$1*' )=' /̀21)%&2$'A*&%1*%&$')3'A$3*/4$3*'L3\"#82/2,'3̂'a&)1$$0/372')='>>̂-]̂\\'DEIJ'B>)3=$&$31$')3' 3̂*$##/7$3*'Y$9*'a&)1$22/37'\"30'>)45%*\"*/)3\"#'-/37%/2*/12GC'A\"4)2,' -LVRH]Y',̀'BDEIDG,'-$2'!&\"/$2'0/==/1%#*+2'0%'=&\"3d\"/2,'N^̀YX̂]A'Ac]LaAH'ǸbH-XaaH_H]Y,' -LVRH]Y',̀']e\\RH'A,'$*'AN\\VN-L'a,'BDEEFG,'-.\"3\"#82$%&'283*\"9/<%$'>)&0/\"#'0\"32'a\"22\"7$,'L1*$2' 0$'YL-]'DEEF'BY&\"/*$4$3*'\"%*)4\"*/<%$'0$2'#\"37%$2'3\"*%&$##$2GC'A$3#/2,'LYL-LC'-â],' -LVRH]Y' ,̀' ]e\\RH' A,' $*' AN\\VN-L' a,' BDEEFG,' L55)&*' 0$2' 1))11%&&$31$2' Q' #\"' 1)&&$1*/)3' $*' Q' #.\"3\"#82$'283*\"9/<%$,'L1*$2'0$'YL-]'DEEF'BY&\"/*$4$3*'\"%*)4\"*/<%$'0$2'#\"37%$2'3\"*%&$##$2GC' A$3#/2,'LYL-LC'-â],' fÂ]ĤfAZ'̂ \\,' _Lg' L,' $*' cbX]' W,' BDEIEG,' R$1%$/#' $*' \"3\"#82$' 0.%3' 1)&5%2' +1)#)7/<%$' 0$' 1)&&$1*/)32' )&*6)7&\"56/<%$2' $9*&\"/*2' 0$2' &+!/2/)32' f/h/5$0/\",' L1*$2' 0$' YL-]' DEIE' BY&\"/*$4$3*'\"%*)4\"*/<%$'0$2'#\"37%$2'3\"*%&$##$2GC'_)3*&+\"#,'LYL-L,' TALN-RÉCITAL 2013, 17-21 Juin, Les Sables d’Olonne 796 c⃝ ATALA"]}]}