{"pubtype":"InProceedings","citekey":"louis-nenkova:2014:EACL","author":"Louis, Annie and Nenkova, Ani","title":"Verbose, Laconic or Just Right: A Simple Computational Model of Content Appropriateness under Length Constraints","booktitle":"Proceedings of the 14th Conference of the European Chapter of the Association for Computational Linguistics","month":"April","year":"2014","address":"Gothenburg, Sweden","publisher":"Association for Computational Linguistics","pages":"636--644","url":"http://www.aclweb.org/anthology/E14-1067"}
