{"pubtype":"InProceedings","citekey":"szumlanski-gomez:2011:CoNLL","author":"Szumlanski, Sean and Gomez, Fernando","title":"Evaluating a Semantic Network Automatically Constructed from Lexical Co-occurrence on a Word Sense Disambiguation Task","booktitle":"Proceedings of the Fifteenth Conference on Computational Natural Language Learning","month":"June","year":"2011","address":"Portland, Oregon, USA","publisher":"Association for Computational Linguistics","pages":"190--199","url":"http://www.aclweb.org/anthology/W11-0322"}
