{"pubtype":"InProceedings","citekey":"suster-vannoord:2014:Coling","author":"Suster, Simon and van Noord, Gertjan","title":"From neighborhood to parenthood: the advantages of dependency representation over bigrams in Brown clustering","booktitle":"Proceedings of COLING 2014, the 25th International Conference on Computational Linguistics: Technical Papers","month":"August","year":"2014","address":"Dublin, Ireland","publisher":"Dublin City University and Association for Computational Linguistics","pages":"1382--1391","url":"http://www.aclweb.org/anthology/C14-1131"}
