{"pubtype":"InProceedings","citekey":"elhadad-EtAl:2013:MultiLing","author":"Elhadad, Michael and Miranda-Jiménez, Sabino and Steinberger, Josef and Giannakopoulos, George","title":"Multi-document multilingual summarization corpus preparation, Part 2: Czech, Hebrew and Spanish","booktitle":"Proceedings of the MultiLing 2013 Workshop on Multilingual Multi-document Summarization","month":"August","year":"2013","address":"Sofia, Bulgaria","publisher":"Association for Computational Linguistics","pages":"13--19","url":"http://www.aclweb.org/anthology/W13-3102"}
