{"pubtype":"InProceedings","citekey":"le-zuidema-scha:2013:CVSC","author":"Le, Phong and Zuidema, Willem and Scha, Remko","title":"Learning from errors: Using vector-based compositional semantics for parse reranking","booktitle":"Proceedings of the Workshop on Continuous Vector Space Models and their Compositionality","month":"August","year":"2013","address":"Sofia, Bulgaria","publisher":"Association for Computational Linguistics","pages":"11--19","url":"http://www.aclweb.org/anthology/W13-3202"}
