{"pubtype":"inproceedings","citekey":"GARCIAMATEO14.739.L14-1579","author":"Carmen Garcia-Mateo and Antonio Cardenal and Xose Luis Regueira and Elisa Fernández Rei and Marta Martinez and Roberto Seara and Roćo Varela and Noeḿ Basanta","url":"http://www.lrec-conf.org/proceedings/lrec2014/pdf/739_Paper.pdf","note":"ACL Anthology Identifier: L14-1579","title":"CORILGA: a Galician Multilevel Annotated Speech Corpus for Linguistic Analysis","booktitle":"Proceedings of the Ninth International Conference on Language Resources and Evaluation (LREC'14)","year":"2014","month":"May","date":"26-31","address":"Reykjavik, Iceland","editor":"Nicoletta Calzolari and Khalid Choukri and Thierry Declerck and Hrafn Loftsson and Bente Maegaard and Joseph Mariani and Asuncion Moreno and Jan Odijk and Stelios Piperidis","publisher":"European Language Resources Association (ELRA)","isbn":"978-2-9517408-8-4","language":"english","pages":"2653--2657"}
