{"pubtype":"InProceedings","citekey":"vsaric-EtAl:2012:STARSEM-SEMEVAL","author":"Šarić, Frane and Glavaš, Goran and Karan, Mladen and Šnajder, Jan and Dalbelo Bašić, Bojana","title":"TakeLab: Systems for Measuring Semantic Text Similarity","booktitle":"*SEM 2012: The First Joint Conference on Lexical and Computational Semantics -- Volume 1: Proceedings of the main conference and the shared task, and Volume 2: Proceedings of the Sixth International Workshop on Semantic Evaluation (SemEval 2012)","month":"7-8 June","year":"2012","address":"Montréal, Canada","publisher":"Association for Computational Linguistics","pages":"441--448","url":"http://www.aclweb.org/anthology/S12-1060"}
