{"pubtype":"InProceedings","citekey":"seppala-barque-nasr:2012:STARSEM-SEMEVAL","author":"Seppälä, Selja and Barque, Lucie and Nasr, Alexis","title":"Extracting a Semantic Lexicon of French Adjectives from a Large Lexicographic Dictionary","booktitle":"*SEM 2012: The First Joint Conference on Lexical and Computational Semantics -- Volume 1: Proceedings of the main conference and the shared task, and Volume 2: Proceedings of the Sixth International Workshop on Semantic Evaluation (SemEval 2012)","month":"7-8 June","year":"2012","address":"Montréal, Canada","publisher":"Association for Computational Linguistics","pages":"161--169","url":"http://www.aclweb.org/anthology/S12-1024"}
