{"pubtype":"InProceedings","citekey":"Baik-Chae:2010:PACLIC2010","author":"Songiy Baik and Hee-Rahk Chae","title":"An Ontological Analysis of Japanese and Chinese Kinship Terms","booktitle":"Proceedings of the 24th Pacific Asia Conference on Language, Information and Computation","year":"2010","month":"November","address":"Tohoku University, Sendai, Japan","publisher":"Institute of Digital Enhancement of Cognitive Processing, Waseda University","pages":"349--356","url":"http://www.aclweb.org/anthology/Y10-1039"}
