{"pubtype":"InProceedings","citekey":"saggion-EtAl:2010:YOUNG","author":"Saggion, Horacio and Stein-Sparvieri, Elena and Maldavsky, David and Szasz, Sandra","title":"Human Language Technology for Text-based Analysis of Psychotherapy Sessions in the Spanish Language","booktitle":"Proceedings of the NAACL HLT 2010 Young Investigators Workshop on Computational Approaches to Languages of the Americas","month":"June","year":"2010","address":"Los Angeles, California","publisher":"Association for Computational Linguistics","pages":"32--39","url":"http://www.aclweb.org/anthology/W10-1605"}
