{"pubtype":"InProceedings","citekey":"keshtkar-inkpen:2010:EMOTION","author":"Keshtkar, Fazel and Inkpen, Diana","title":"A Corpus-based Method for Extracting Paraphrases of Emotion Terms","booktitle":"Proceedings of the NAACL HLT 2010 Workshop on Computational Approaches to Analysis and Generation of Emotion in Text","month":"June","year":"2010","address":"Los Angeles, CA","publisher":"Association for Computational Linguistics","pages":"35--44","url":"http://www.aclweb.org/anthology/W10-0205"}
