{"pubtype":"InProceedings","citekey":"pan-mulkar-hobbs:2006:COLACL","author":"Pan, Feng and Mulkar, Rutu and Hobbs, Jerry R.","title":"Learning Event Durations from Event Descriptions","booktitle":"Proceedings of the 21st International Conference on Computational Linguistics and 44th Annual Meeting of the Association for Computational Linguistics","month":"July","year":"2006","address":"Sydney, Australia","publisher":"Association for Computational Linguistics","pages":"393--400","url":"http://www.aclweb.org/anthology/P06-1050","doi":"10.3115/1220175.1220225"}
