{"pubtype":"inproceedings","citekey":"kessler-EtAl:2014:TALN","author":"Kessler, Re패my and Be패chet, Nicolas and Laplante, Audrey and Forest, Dominic","title":"Music period detection of music collections using learning techniques (De패tection de pe패riodes musicales d'une collection de musique par apprentissage) [in French]","booktitle":"Proceedings of TALN 2014 (Volume 2: Short Papers)","month":"July","year":"2014","address":"Marseille, France","publisher":"Association pour le Traitement Automatique des Langues","pages":"461--466","url":"http://www.aclweb.org/anthology/F14-2013"}
