{"pubtype":"InProceedings","citekey":"hsu:2014:CogALex","author":"Hsu, Chan-Chia","title":"When Frequency Data Meet Dispersion Data in the Extraction of Multi-word Units from a Corpus: A Study of Trigrams in Chinese","booktitle":"Proceedings of the 4th Workshop on Cognitive Aspects of the Lexicon (CogALex)","month":"August","year":"2014","address":"Dublin, Ireland","publisher":"Association for Computational Linguistics and Dublin City University","pages":"99--104","url":"http://www.aclweb.org/anthology/W14-4714"}
