{"pubtype":"InProceedings","citekey":"lamers-EtAl:2014:W14-32","author":"Lamers, Sanne M.A. and Truong, Khiet P. and Steunenberg, Bas and de Jong, Franciska and Westerhof, Gerben J.","title":"Applying prosodic speech features in mental health care: An exploratory study in a life-review intervention for depression","booktitle":"Proceedings of the Workshop on Computational Linguistics and Clinical Psychology: From Linguistic Signal to Clinical Reality","month":"June","year":"2014","address":"Baltimore, Maryland, USA","publisher":"Association for Computational Linguistics","pages":"61--68","url":"http://www.aclweb.org/anthology/W14-3208"}
