{"pubtype":"InProceedings","citekey":"iosif-mishra:2014:CLFL","author":"Iosif, Elias and Mishra, Taniya","title":"From Speaker Identification to Affective Analysis: A Multi-Step System for Analyzing Children's Stories","booktitle":"Proceedings of the 3rd Workshop on Computational Linguistics for Literature (CLFL)","month":"April","year":"2014","address":"Gothenburg, Sweden","publisher":"Association for Computational Linguistics","pages":"40--49","url":"http://www.aclweb.org/anthology/W14-0906"}
