{"pubtype":"InProceedings","citekey":"isemann-lynch-lanino:2014:SWAIE","author":"Isemann, Daniel and Lynch, Gerard and Lanino, Raffaella","title":"Towards a robust framework for the semantic representation of temporal expressions in cultural legacy data","booktitle":"Proceedings of the Third Workshop on Semantic Web and Information Extraction","month":"August","year":"2014","address":"Dublin, Ireland","publisher":"Association for Computational Linguistics and Dublin City University","pages":"41--50","url":"http://www.aclweb.org/anthology/W14-6206"}
