{"pubtype":"InProceedings","citekey":"kaplan-iida-tokunaga:2009:NLPIR4DL","author":"Kaplan, Dain and Iida, Ryu and Tokunaga, Takenobu","title":"Automatic Extraction of Citation Contexts for Research Paper Summarization: A Coreference-chain based Approach","booktitle":"Proceedings of the 2009 Workshop on Text and Citation Analysis for Scholarly Digital Libraries","month":"August","year":"2009","address":"Suntec City, Singapore","publisher":"Association for Computational Linguistics","pages":"88--95","url":"http://www.aclweb.org/anthology/W/W09/W09-3611"}
