{"pubtype":"InProceedings","citekey":"pestian-EtAl:2007:BioNLP","author":"Pestian, John P. and Brew, Chris and Matykiewicz, Pawel and Hovermale, DJ and Johnson, Neil and Cohen, K. Bretonnel and Duch, Wlodzislaw","title":"A shared task involving multi-label classification of clinical free text","booktitle":"Biological, translational, and clinical language processing","month":"June","year":"2007","address":"Prague, Czech Republic","publisher":"Association for Computational Linguistics","pages":"97--104","url":"http://www.aclweb.org/anthology/W/W07/W07-1013"}
